<annotation>
	<folder>sanImagesresized</folder>
	<filename>image96.jpeg</filename>
	<path>/Users/krishna/Creative_Man/AI_ML/JobPrep/SanitizerPOC/sanImagesresized/image96.jpeg</path>
	<source>
		<database>Unknown</database>
	</source>
	<size>
		<width>400</width>
		<height>600</height>
		<depth>3</depth>
	</size>
	<segmented>0</segmented>
	<object>
		<name>handsanitizer</name>
		<pose>Unspecified</pose>
		<truncated>0</truncated>
		<difficult>0</difficult>
		<bndbox>
			<xmin>83</xmin>
			<ymin>102</ymin>
			<xmax>330</xmax>
			<ymax>555</ymax>
		</bndbox>
	</object>
</annotation>
